metworkpy-0.2.7.dist-info/METADATA
metworkpy-0.2.7.dist-info/WHEEL
metworkpy-0.2.7.dist-info/entry_points.txt
metworkpy-0.2.7.dist-info/licenses/LICENSE
metworkpy/__init__.py
metworkpy/divergence/__init__.py
metworkpy/divergence/_data_validation.py
metworkpy/divergence/_main_wrapper.py
metworkpy/divergence/_pairwise_divergence.py
metworkpy/divergence/group_divergence.py
metworkpy/divergence/js_divergence_functions.py
metworkpy/divergence/kl_divergence_exact.py
metworkpy/divergence/kl_divergence_functions.py
metworkpy/divergence/ko_divergence_functions.py
metworkpy/gpr/__init__.py
metworkpy/gpr/gpr_functions.py
metworkpy/imat/__init__.py
metworkpy/imat/imat_functions.py
metworkpy/imat/imat_iter.py
metworkpy/imat/model_creation.py
metworkpy/information/__init__.py
metworkpy/information/mutual_information_functions.py
metworkpy/information/mutual_information_network.py
metworkpy/metabolites/__init__.py
metworkpy/metabolites/metabolite_network.py
metworkpy/metabolites/metchange_functions.py
metworkpy/network/__init__.py
metworkpy/network/_array_utils.py
metworkpy/network/density.py
metworkpy/network/network_construction.py
metworkpy/network/projection.py
metworkpy/py.typed
metworkpy/rank_entropy/__init__.py
metworkpy/rank_entropy/_bootstrap_pvalue.py
metworkpy/rank_entropy/_datagen.py
metworkpy/rank_entropy/crane_functions.py
metworkpy/rank_entropy/dirac_functions.py
metworkpy/rank_entropy/infer_functions.py
metworkpy/rank_entropy/race_functions.py
metworkpy/rank_entropy/rank_entropy_exceptions.py
metworkpy/scripts/__init__.py
metworkpy/scripts/_script_utils.py
metworkpy/scripts/imatgen.py
metworkpy/scripts/metchange.py
metworkpy/scripts/metdivergence.py
metworkpy/scripts/metsample.py
metworkpy/synleth/__init__.py
metworkpy/synleth/fastess.py
metworkpy/synleth/fastsl.py
metworkpy/utils/__init__.py
metworkpy/utils/_arguments.py
metworkpy/utils/_jitter.py
metworkpy/utils/_parallel.py
metworkpy/utils/expression_utils.py
metworkpy/utils/models.py
metworkpy/utils/translate.py
metworkpy-0.2.7.dist-info/RECORD
