Metadata-Version: 2.1
Name: metworkpy
Version: 0.2.7
Summary: Tools for creating and working with network models of metabolism.
Keywords: FBA,metabolism,IMAT,metchange
Author-Email: Braden Griebel <bgriebel@uw.edu>
License: MIT
Project-URL: Homepage, https://github.com/Ma-Lab-Seattle-Childrens-CGIDR/metworkpy
Project-URL: Repository, https://github.com/Ma-Lab-Seattle-Childrens-CGIDR/metworkpy
Project-URL: Documentation, https://metworkpy.readthedocs.io/en/latest/
Project-URL: Issues, https://github.com/Ma-Lab-Seattle-Childrens-CGIDR/metworkpy/issues
Project-URL: Changelog, https://github.com/Ma-Lab-Seattle-Childrens-CGIDR/metworkpy/blob/main/CHANGELOG.md
Requires-Python: <3.14,>=3.9
Requires-Dist: cobra>=0.30.0
Requires-Dist: scipy>=1.12.0
Requires-Dist: networkx>=3.2.1
Requires-Dist: pandas>=2.2.0
Requires-Dist: numpy>=1.26
Requires-Dist: optlang>=1.8.1
Requires-Dist: sympy>=1.12
Requires-Dist: tqdm>=4.66.4
Requires-Dist: pyarrow>=16.0.0
Requires-Dist: joblib>=1.4.2
Provides-Extra: cplex
Requires-Dist: cplex>=22.1.1.1; extra == "cplex"
Provides-Extra: gurobi
Requires-Dist: gurobipy>=11.0.0; extra == "gurobi"
Provides-Extra: fastparquet
Requires-Dist: fastparquet>=2024.5.0; extra == "fastparquet"
Provides-Extra: excel
Requires-Dist: openpyxl>=3.1.4; extra == "excel"
Provides-Extra: hybrid
Requires-Dist: highspy>=1.10.0; extra == "hybrid"
Requires-Dist: osqp>=1.0.3; extra == "hybrid"
